DataFetcher.py
dataset_fetcher-1.0.0.dist-info/LICENSE
dataset_fetcher-1.0.0.dist-info/METADATA
dataset_fetcher-1.0.0.dist-info/WHEEL
dataset_fetcher-1.0.0.dist-info/top_level.txt
dataset_fetcher-1.0.0.dist-info/RECORD
