Metadata-Version: 2.1
Name: dataset-fetcher
Version: 1.0.0
Summary: A package for fetching datasets for Analytics purposes
Author: DATAISENOUGH
Author-email: dataisenough@gmail.com
Classifier: Programming Language :: Python :: 3
Classifier: License :: OSI Approved :: MIT License
Classifier: Operating System :: OS Independent
Requires-Python: >=3.8
License-File: LICENSE
Requires-Dist: pandas
Requires-Dist: requests
Requires-Dist: tabulate
